voiceos/__init__.py
voiceos/api_client.py
voiceos/api_response.py
voiceos/client.py
voiceos/configuration.py
voiceos/exceptions.py
voiceos/py.typed
voiceos/rest.py
voiceos/api/__init__.py
voiceos/api/agents_api.py
voiceos/api/conversations_api.py
voiceos/api/default_api.py
voiceos/api/phone_numbers_api.py
voiceos/models/__init__.py
voiceos/models/agent_configuration.py
voiceos/models/agent_cost.py
voiceos/models/agent_pagination.py
voiceos/models/agent_provider.py
voiceos/models/agent_response.py
voiceos/models/azure_languages.py
voiceos/models/azure_model.py
voiceos/models/azure_transcriber.py
voiceos/models/azure_transcriber_languages_inner.py
voiceos/models/azure_voice.py
voiceos/models/buy_phone_number.py
voiceos/models/chat_gpt.py
voiceos/models/conversation_cost.py
voiceos/models/conversation_recording.py
voiceos/models/conversation_response.py
voiceos/models/conversation_status.py
voiceos/models/conversation_type.py
voiceos/models/conversations_pagination.py
voiceos/models/create_call.py
voiceos/models/deepgram_languages.py
voiceos/models/deepgram_transcriber.py
voiceos/models/deepgram_voice.py
voiceos/models/eleven_labs_model.py
voiceos/models/eleven_labs_voices.py
voiceos/models/elevenlabs_voice.py
voiceos/models/ended_reasons.py
voiceos/models/event_name.py
voiceos/models/http_validation_error.py
voiceos/models/language.py
voiceos/models/language_model_cost.py
voiceos/models/message.py
voiceos/models/message_role.py
voiceos/models/method_enum.py
voiceos/models/model.py
voiceos/models/model1.py
voiceos/models/model2.py
voiceos/models/model3.py
voiceos/models/model4.py
voiceos/models/open_ai.py
voiceos/models/phone_number.py
voiceos/models/phone_number_events.py
voiceos/models/phone_number_pagination.py
voiceos/models/phone_number_response.py
voiceos/models/phone_number_to_buy.py
voiceos/models/phone_number_webhook.py
voiceos/models/play_ht_model.py
voiceos/models/playht_voice.py
voiceos/models/rime_speaker.py
voiceos/models/rime_voice.py
voiceos-0.8.1.3.dist-info/METADATA
voiceos-0.8.1.3.dist-info/WHEEL
voiceos-0.8.1.3.dist-info/top_level.txt
voiceos-0.8.1.3.dist-info/RECORD
