Metadata-Version: 2.1
Name: voiceos
Version: 0.8.1.3
Summary: VoiceOS Python SDK
Home-page: https://github.com/WakoAi/voiceos-python
Author: WakoAI
Author-email: hello@wako.ai
Keywords: VoiceOS,VoiceOS Python ClientSDK,VoiceOS Python
Requires-Dist: urllib3 (<2.1.0,>=1.25.3)
Requires-Dist: python-dateutil
Requires-Dist: pydantic (>=2)
Requires-Dist: typing-extensions (>=4.7.1)
